gertrude/__init__.py
gertrude/application/__init__.py
gertrude/application/projectors.py
gertrude/application/use_cases/__init__.py
gertrude/application/use_cases/assign_task.py
gertrude/application/use_cases/capture_task.py
gertrude/application/use_cases/create_project.py
gertrude/application/use_cases/delegate_task.py
gertrude/application/use_cases/display_project.py
gertrude/application/use_cases/do_task.py
gertrude/application/use_cases/eliminate_task.py
gertrude/application/use_cases/file_task.py
gertrude/application/use_cases/incubate_task.py
gertrude/application/use_cases/list_next_tasks.py
gertrude/application/use_cases/list_projects.py
gertrude/application/use_cases/list_tasks.py
gertrude/application/use_cases/postpone_task.py
gertrude/application/use_cases/reclaim_task.py
gertrude/application/use_cases/schedule_task.py
gertrude/application/use_cases/update_task.py
gertrude/configuration/__init__.py
gertrude/configuration/cli.py
gertrude/configuration/wsgi.py
gertrude/domain/__init__.py
gertrude/domain/project_management/__init__.py
gertrude/domain/project_management/entities.py
gertrude/domain/project_management/repositories.py
gertrude/domain/project_management/value_objects.py
gertrude/domain/task_management/__init__.py
gertrude/domain/task_management/dto.py
gertrude/domain/task_management/entities.py
gertrude/domain/task_management/enums.py
gertrude/domain/task_management/events.py
gertrude/domain/task_management/exceptions.py
gertrude/domain/task_management/projections.py
gertrude/domain/task_management/repositories.py
gertrude/domain/task_management/services.py
gertrude/domain/task_management/value_objects.py
gertrude/infrastructure/__init__.py
gertrude/infrastructure/click/__init__.py
gertrude/infrastructure/flask/__init__.py
gertrude/infrastructure/flask/auth/__init__.py
gertrude/infrastructure/flask/ip/__init__.py
gertrude/infrastructure/flask/projects/__init__.py
gertrude/infrastructure/flask/root/__init__.py
gertrude-0.1.0a21.dist-info/COPYING
gertrude-0.1.0a21.dist-info/METADATA
gertrude-0.1.0a21.dist-info/WHEEL
gertrude-0.1.0a21.dist-info/entry_points.txt
gertrude-0.1.0a21.dist-info/RECORD
